oyunlayiciapi/__init__.py
oyunlayiciapi/main.py
oyunlayiciapi-0.0.3.dist-info/METADATA
oyunlayiciapi-0.0.3.dist-info/WHEEL
oyunlayiciapi-0.0.3.dist-info/top_level.txt
oyunlayiciapi-0.0.3.dist-info/RECORD
