Metadata-Version: 2.1
Name: oyunlayiciapi
Version: 0.0.3
Summary: Minecraft sunucularından bilgi almaya yarayan Oyunlayıcı API kütüphanesi
Author: mavi_v
Requires-Dist: requests >=2.31.0
